ovos_skill_wordnet/__init__.py
ovos_skill_wordnet/version.py
ovos_skill_wordnet/locale/ca-es/antonym.intent
ovos_skill_wordnet/locale/ca-es/definition.intent
ovos_skill_wordnet/locale/ca-es/holonym.intent
ovos_skill_wordnet/locale/ca-es/hypernym.intent
ovos_skill_wordnet/locale/ca-es/hyponym.intent
ovos_skill_wordnet/locale/ca-es/lemma.intent
ovos_skill_wordnet/locale/ca-es/no_answer.dialog
ovos_skill_wordnet/locale/ca-es/search_wordnet.intent
ovos_skill_wordnet/locale/ca-es/skill.json
ovos_skill_wordnet/locale/da-dk/antonym.intent
ovos_skill_wordnet/locale/da-dk/definition.intent
ovos_skill_wordnet/locale/da-dk/holonym.intent
ovos_skill_wordnet/locale/da-dk/hypernym.intent
ovos_skill_wordnet/locale/da-dk/hyponym.intent
ovos_skill_wordnet/locale/da-dk/lemma.intent
ovos_skill_wordnet/locale/da-dk/no_answer.dialog
ovos_skill_wordnet/locale/da-dk/search_wordnet.intent
ovos_skill_wordnet/locale/da-dk/skill.json
ovos_skill_wordnet/locale/de-de/antonym.intent
ovos_skill_wordnet/locale/de-de/definition.intent
ovos_skill_wordnet/locale/de-de/holonym.intent
ovos_skill_wordnet/locale/de-de/hypernym.intent
ovos_skill_wordnet/locale/de-de/hyponym.intent
ovos_skill_wordnet/locale/de-de/lemma.intent
ovos_skill_wordnet/locale/de-de/no_answer.dialog
ovos_skill_wordnet/locale/de-de/search_wordnet.intent
ovos_skill_wordnet/locale/de-de/skill.json
ovos_skill_wordnet/locale/en-us/antonym.intent
ovos_skill_wordnet/locale/en-us/definition.intent
ovos_skill_wordnet/locale/en-us/holonym.intent
ovos_skill_wordnet/locale/en-us/hypernym.intent
ovos_skill_wordnet/locale/en-us/hyponym.intent
ovos_skill_wordnet/locale/en-us/lemma.intent
ovos_skill_wordnet/locale/en-us/no_answer.dialog
ovos_skill_wordnet/locale/en-us/search_wordnet.intent
ovos_skill_wordnet/locale/en-us/skill.json
ovos_skill_wordnet/locale/es-es/antonym.intent
ovos_skill_wordnet/locale/es-es/definition.intent
ovos_skill_wordnet/locale/es-es/holonym.intent
ovos_skill_wordnet/locale/es-es/hypernym.intent
ovos_skill_wordnet-0.2.6.dist-info/licenses/LICENSE
ovos_skill_wordnet-0.2.6.dist-info/METADATA
ovos_skill_wordnet-0.2.6.dist-info/WHEEL
ovos_skill_wordnet-0.2.6.dist-info/entry_points.txt
ovos_skill_wordnet-0.2.6.dist-info/top_level.txt
ovos_skill_wordnet-0.2.6.dist-info/RECORD
