Metadata-Version: 2.4
Name: ovos_skill_wordnet
Version: 0.2.6
Summary: ovos Wordnet skill plugin
Home-page: https://github.com/OpenVoiceOS/ovos-skill-wordnet
Author: JarbasAi
Author-email: jarbasai@mailfence.com
License: Apache-2.0
Keywords: ovos skill plugin
License-File: LICENSE
Requires-Dist: ovos_workshop<8.0.0,>=3.3.0
Requires-Dist: ovos-translate-server-plugin
Requires-Dist: ovos-plugin-manager<3.0.0,>=0.0.26
Dynamic: author
Dynamic: author-email
Dynamic: description
Dynamic: description-content-type
Dynamic: home-page
Dynamic: keywords
Dynamic: license
Dynamic: license-file
Dynamic: requires-dist
Dynamic: summary
